davidkhala/baidu/map/__init__.py
davidkhala_baidu_map-0.0.2.dist-info/METADATA
davidkhala_baidu_map-0.0.2.dist-info/WHEEL
davidkhala_baidu_map-0.0.2.dist-info/RECORD
