Metadata-Version: 2.4
Name: davidkhala.baidu.map
Version: 0.0.2
Author-email: David Liu <david-khala@hotmail.com>
Requires-Python: >=3.10
Requires-Dist: davidkhala-utils[http-request]
